README.md
setup.py
ourkids/ExceptionBuilder.py
ourkids/ExceptionInterceptor.py
ourkids/ExceptionView.py
ourkids/NotAuthException.py
ourkids/NotFoundException.py
ourkids/ResponseBuilder.py
ourkids/Settings.py
ourkids/__init__.py
ourkids/database.py
ourkids/exceptionBody.py
ourkids/interceptors.py
ourkids/load.py
ourkids/response.py
ourkids_common.egg-info/PKG-INFO
ourkids_common.egg-info/SOURCES.txt
ourkids_common.egg-info/dependency_links.txt
ourkids_common.egg-info/requires.txt
ourkids_common.egg-info/top_level.txt