Metadata-Version: 2.1
Name: ourkids-common
Version: 0.0.4
Summary: Librería para tener configuraciones y archivos comunes para la implementación y uso de servidores en flask.
Home-page: https://github.com/Jefry-bot/Common-OurKids
Download-URL: https://github.com/Jefry-bot/Common-OurKids/tarball/0.0.1
Author: Jefry Zárate Ruíz
Author-email: jefryzarateruiz@gmail.com
License: MIT
